{
  "config": {
    "client_algorithm": "sgd",
    "client_batch_size": 32,
    "client_lr": 0.01,
    "client_n_epochs": 4,
    "client_selection_fraction": 0.3,
    "clients_distribution": "balanced",
    "clients_mobility": true,
    "dataset_distribution": "non_iid",
    "dataset_name": "cifar10",
    "debug": false,
    "epochs_delay_localSGD": 5,
    "log_frequency": 1,
    "log_verbosity": 2,
    "lr_warmup": false,
    "mobility_rate": 0.5,
    "model_init": "random",
    "model_type": "mobileNet",
    "n_clients": 250,
    "n_clusters": 25,
    "server_global_rate": 3,
    "stdout_frequency": 1,
    "stdout_verbosity": 2,
    "stop_condition": "rounds",
    "stop_value": 500,
    "log_file": "log_files/cifar_sgd_local_postlocal-31"
  },
  "results": {
    "rounds": [
      1,
      2,
      3,
      4,
      5,
      6,
      7,
      8,
      9,
      10,
      11,
      12,
      13,
      14,
      15,
      16,
      17,
      18,
      19,
      20,
      21,
      22,
      23,
      24,
      25,
      26,
      27,
      28,
      29,
      30,
      31,
      32,
      33,
      34,
      35,
      36,
      37,
      38,
      39,
      40,
      41,
      42,
      43,
      44,
      45,
      46,
      47,
      48,
      49,
      50,
      51,
      52,
      53,
      54,
      55,
      56,
      57,
      58,
      59,
      60,
      61,
      62,
      63,
      64,
      65,
      66,
      67,
      68,
      69,
      70,
      71,
      72,
      73,
      74,
      75,
      76,
      77,
      78,
      79,
      80,
      81,
      82,
      83,
      84,
      85,
      86,
      87,
      88,
      89,
      90,
      91,
      92,
      93,
      94,
      95,
      96,
      97,
      98,
      99,
      100,
      101,
      102,
      103,
      104,
      105,
      106,
      107,
      108,
      109,
      110,
      111,
      112,
      113,
      114,
      115,
      116,
      117,
      118,
      119,
      120,
      121,
      122,
      123,
      124,
      125,
      126,
      127,
      128,
      129,
      130,
      131,
      132,
      133,
      134,
      135,
      136,
      137,
      138,
      139,
      140,
      141,
      142,
      143,
      144,
      145,
      146,
      147,
      148,
      149,
      150,
      151,
      152,
      153,
      154,
      155,
      156,
      157,
      158,
      159,
      160,
      161,
      162,
      163,
      164,
      165,
      166,
      167,
      168,
      169,
      170,
      171,
      172,
      173,
      174,
      175,
      176,
      177,
      178,
      179,
      180,
      181,
      182,
      183,
      184,
      185,
      186,
      187,
      188,
      189,
      190,
      191,
      192,
      193,
      194,
      195,
      196,
      197,
      198,
      199,
      200,
      201,
      202,
      203,
      204,
      205,
      206,
      207,
      208,
      209,
      210,
      211,
      212,
      213,
      214,
      215,
      216,
      217,
      218,
      219,
      220,
      221,
      222,
      223,
      224,
      225,
      226,
      227,
      228,
      229,
      230,
      231,
      232,
      233,
      234,
      235,
      236,
      237,
      238,
      239,
      240,
      241,
      242,
      243,
      244,
      245,
      246,
      247,
      248,
      249,
      250,
      251,
      252,
      253,
      254,
      255,
      256,
      257,
      258,
      259,
      260,
      261,
      262,
      263,
      264,
      265,
      266,
      267,
      268,
      269,
      270,
      271,
      272,
      273,
      274,
      275,
      276,
      277,
      278,
      279,
      280,
      281,
      282,
      283,
      284,
      285,
      286,
      287,
      288,
      289,
      290,
      291,
      292,
      293,
      294,
      295,
      296,
      297,
      298,
      299,
      300,
      301,
      302,
      303,
      304,
      305,
      306,
      307,
      308,
      309,
      310,
      311,
      312,
      313,
      314,
      315,
      316,
      317,
      318,
      319,
      320,
      321,
      322,
      323,
      324,
      325,
      326,
      327,
      328,
      329,
      330,
      331,
      332,
      333,
      334,
      335,
      336,
      337,
      338,
      339,
      340,
      341,
      342,
      343,
      344,
      345,
      346,
      347,
      348,
      349,
      350,
      351,
      352,
      353,
      354,
      355,
      356,
      357,
      358,
      359,
      360,
      361,
      362,
      363,
      364,
      365,
      366,
      367,
      368,
      369,
      370,
      371,
      372,
      373,
      374,
      375,
      376,
      377,
      378,
      379,
      380,
      381,
      382,
      383,
      384,
      385,
      386,
      387,
      388,
      389,
      390,
      391,
      392,
      393,
      394,
      395,
      396,
      397,
      398,
      399,
      400,
      401,
      402,
      403,
      404,
      405,
      406,
      407,
      408,
      409,
      410,
      411,
      412,
      413,
      414,
      415,
      416,
      417,
      418,
      419,
      420,
      421,
      422,
      423,
      424,
      425,
      426,
      427,
      428,
      429,
      430,
      431,
      432,
      433,
      434,
      435,
      436,
      437,
      438,
      439,
      440,
      441,
      442,
      443,
      444,
      445,
      446,
      447,
      448,
      449,
      450,
      451,
      452,
      453,
      454,
      455,
      456,
      457,
      458,
      459,
      460,
      461,
      462,
      463,
      464,
      465,
      466,
      467,
      468,
      469,
      470,
      471,
      472,
      473,
      474,
      475,
      476,
      477,
      478,
      479,
      480,
      481,
      482,
      483,
      484,
      485,
      486,
      487,
      488,
      489,
      490,
      491,
      492,
      493,
      494,
      495,
      496,
      497,
      498,
      499,
      500
    ],
    "train_accuracy": [
      0.0,
      0.0,
      0.0,
      0.0,
      0.0,
      0.0,
      0.0,
      0.0,
      0.0,
      0.0,
      0.0,
      0.0,
      0.0,
      0.0,
      0.0,
      0.0,
      0.0,
      0.0,
      0.0,
      0.0,
      0.0,
      0.0,
      0.0,
      0.0,
      0.0,
      0.0,
      0.0,
      0.0,
      0.0,
      0.0,
      0.0,
      0.0,
      0.0,
      0.0,
      0.0,
      0.0,
      0.0,
      0.0,
      0.0,
      0.0,
      0.0,
      0.0,
      0.0,
      0.0,
      0.0,
      0.0,
      0.0,
      0.0,
      0.0,
      0.0,
      0.0,
      0.0,
      0.0,
      0.0,
      0.0,
      0.0,
      0.0,
      0.0,
      0.0,
      0.0,
      0.0,
      0.0,
      0.0,
      0.0,
      0.0,
      0.0,
      0.0,
      0.0,
      0.0,
      0.0,
      0.0,
      0.0,
      0.0,
      0.0,
      0.0,
      0.0,
      0.0,
      0.0,
      0.0,
      0.0,
      0.0,
      0.0,
      0.0,
      0.0,
      0.0,
      0.0,
      0.0,
      0.0,
      0.0,
      0.0,
      0.0,
      0.0,
      0.0,
      0.0,
      0.0,
      0.0,
      0.0,
      0.0,
      0.0,
      0.0,
      0.0,
      0.0,
      0.0,
      0.0,
      0.0,
      0.0,
      0.0,
      0.0,
      0.0,
      0.0,
      0.0,
      0.0,
      0.0,
      0.0,
      0.0,
      0.0,
      0.0,
      0.0,
      0.0,
      0.0,
      0.0,
      0.0,
      0.0,
      0.0,
      0.0,
      0.0,
      0.0,
      0.0,
      0.0,
      0.0,
      0.0,
      0.0,
      0.0,
      0.0,
      0.0,
      0.0,
      0.0,
      0.0,
      0.0,
      0.0,
      0.0,
      0.0,
      0.0,
      0.0,
      0.0,
      0.0,
      0.0,
      0.0,
      0.0,
      0.0,
      0.0,
      0.0,
      0.0,
      0.0,
      0.0,
      0.0,
      0.0,
      0.0,
      0.0,
      0.0,
      0.0,
      0.0,
      0.0,
      0.0,
      0.0,
      0.0,
      0.0,
      0.0,
      0.0,
      0.0,
      0.0,
      0.0,
      0.0,
      0.0,
      0.0,
      0.0,
      0.0,
      0.0,
      0.0,
      0.0,
      0.0,
      0.0,
      0.0,
      0.0,
      0.0,
      0.0,
      0.0,
      0.0,
      0.0,
      0.0,
      0.0,
      0.0,
      0.0,
      0.0,
      0.0,
      0.0,
      0.0,
      0.0,
      0.0,
      0.0,
      0.0,
      0.0,
      0.0,
      0.0,
      0.0,
      0.0,
      0.0,
      0.0,
      0.0,
      0.0,
      0.0,
      0.0,
      0.0,
      0.0,
      0.0,
      0.0,
      0.0,
      0.0,
      0.0,
      0.0,
      0.0,
      0.0,
      0.0,
      0.0,
      0.0,
      0.0,
      0.0,
      0.0,
      0.0,
      0.0,
      0.0,
      0.0,
      0.0,
      0.0,
      0.0,
      0.0,
      0.0,
      0.0,
      0.0,
      0.0,
      0.0,
      0.0,
      0.0,
      0.0,
      0.0,
      0.0,
      0.0,
      0.0,
      0.0,
      0.0,
      0.0,
      0.0,
      0.0,
      0.0,
      0.0,
      0.0,
      0.0,
      0.0,
      0.0,
      0.0,
      0.0,
      0.0,
      0.0,
      0.0,
      0.0,
      0.0,
      0.0,
      0.0,
      0.0,
      0.0,
      0.0,
      0.0,
      0.0,
      0.0,
      0.0,
      0.0,
      0.0,
      0.0,
      0.0,
      0.0,
      0.0,
      0.0,
      0.0,
      0.0,
      0.0,
      0.0,
      0.0,
      0.0,
      0.0,
      0.0,
      0.0,
      0.0,
      0.0,
      0.0,
      0.0,
      0.0,
      0.0,
      0.0,
      0.0,
      0.0,
      0.0,
      0.0,
      0.0,
      0.0,
      0.0,
      0.0,
      0.0,
      0.0,
      0.0,
      0.0,
      0.0,
      0.0,
      0.0,
      0.0,
      0.0,
      0.0,
      0.0,
      0.0,
      0.0,
      0.0,
      0.0,
      0.0,
      0.0,
      0.0,
      0.0,
      0.0,
      0.0,
      0.0,
      0.0,
      0.0,
      0.0,
      0.0,
      0.0,
      0.0,
      0.0,
      0.0,
      0.0,
      0.0,
      0.0,
      0.0,
      0.0,
      0.0,
      0.0,
      0.0,
      0.0,
      0.0,
      0.0,
      0.0,
      0.0,
      0.0,
      0.0,
      0.0,
      0.0,
      0.0,
      0.0,
      0.0,
      0.0,
      0.0,
      0.0,
      0.0,
      0.0,
      0.0,
      0.0,
      0.0,
      0.0,
      0.0,
      0.0,
      0.0,
      0.0,
      0.0,
      0.0,
      0.0,
      0.0,
      0.0,
      0.0,
      0.0,
      0.0,
      0.0,
      0.0,
      0.0,
      0.0,
      0.0,
      0.0,
      0.0,
      0.0,
      0.0,
      0.0,
      0.0,
      0.0,
      0.0,
      0.0,
      0.0,
      0.0,
      0.0,
      0.0,
      0.0,
      0.0,
      0.0,
      0.0,
      0.0,
      0.0,
      0.0,
      0.0,
      0.0,
      0.0,
      0.0,
      0.0,
      0.0,
      0.0,
      0.0,
      0.0,
      0.0,
      0.0,
      0.0,
      0.0,
      0.0,
      0.0,
      0.0,
      0.0,
      0.0,
      0.0,
      0.0,
      0.0,
      0.0,
      0.0,
      0.0,
      0.0,
      0.0,
      0.0,
      0.0,
      0.0,
      0.0,
      0.0,
      0.0,
      0.0,
      0.0,
      0.0,
      0.0,
      0.0,
      0.0,
      0.0,
      0.0,
      0.0,
      0.0,
      0.0,
      0.0,
      0.0,
      0.0,
      0.0,
      0.0,
      0.0,
      0.0,
      0.0,
      0.0,
      0.0,
      0.0,
      0.0,
      0.0,
      0.0,
      0.0,
      0.0,
      0.0,
      0.0,
      0.0,
      0.0,
      0.0,
      0.0,
      0.0,
      0.0,
      0.0,
      0.0,
      0.0,
      0.0,
      0.0,
      0.0,
      0.0,
      0.0,
      0.0,
      0.0,
      0.0,
      0.0,
      0.0,
      0.0,
      0.0,
      0.0,
      0.0,
      0.0,
      0.0,
      0.0,
      0.0,
      0.0,
      0.0,
      0.0,
      0.0,
      0.0,
      0.0,
      0.0,
      0.0,
      0.0,
      0.0
    ],
    "test_accuracy": [
      0.0,
      0.0,
      0.1128,
      0.1128,
      0.1128,
      0.10985,
      0.10985,
      0.10985,
      0.112,
      0.112,
      0.112,
      0.11480000000000001,
      0.11480000000000001,
      0.11480000000000001,
      0.11495,
      0.11495,
      0.11495,
      0.11430000000000001,
      0.11430000000000001,
      0.11430000000000001,
      0.10065,
      0.10065,
      0.10065,
      0.10175000000000001,
      0.10175000000000001,
      0.10175000000000001,
      0.09970000000000001,
      0.09970000000000001,
      0.09970000000000001,
      0.10495,
      0.10495,
      0.10495,
      0.1089,
      0.1089,
      0.1089,
      0.10825,
      0.10825,
      0.10825,
      0.11755,
      0.11755,
      0.11755,
      0.11449999999999999,
      0.11449999999999999,
      0.11449999999999999,
      0.12545,
      0.12545,
      0.12545,
      0.13645,
      0.13645,
      0.13645,
      0.13035,
      0.13035,
      0.13035,
      0.14350000000000002,
      0.14350000000000002,
      0.14350000000000002,
      0.14385,
      0.14385,
      0.14385,
      0.15289999999999998,
      0.15289999999999998,
      0.15289999999999998,
      0.1552,
      0.1552,
      0.1552,
      0.14185,
      0.14185,
      0.14185,
      0.15665,
      0.15665,
      0.15665,
      0.1805,
      0.1805,
      0.1805,
      0.187,
      0.187,
      0.187,
      0.15095,
      0.15095,
      0.15095,
      0.1736,
      0.1736,
      0.1736,
      0.17125,
      0.17125,
      0.17125,
      0.19169999999999998,
      0.19169999999999998,
      0.19169999999999998,
      0.17325000000000002,
      0.17325000000000002,
      0.17325000000000002,
      0.1974,
      0.1974,
      0.1974,
      0.1691,
      0.1691,
      0.1691,
      0.1895,
      0.1895,
      0.1895,
      0.15084999999999998,
      0.15084999999999998,
      0.15084999999999998,
      0.19475,
      0.19475,
      0.19475,
      0.16115,
      0.16115,
      0.16115,
      0.1724,
      0.1724,
      0.1724,
      0.21989999999999998,
      0.21989999999999998,
      0.21989999999999998,
      0.2082,
      0.2082,
      0.2082,
      0.22655,
      0.22655,
      0.22655,
      0.18445,
      0.18445,
      0.18445,
      0.1896,
      0.1896,
      0.1896,
      0.17835,
      0.17835,
      0.17835,
      0.16585,
      0.16585,
      0.16585,
      0.16745,
      0.16745,
      0.16745,
      0.16394999999999998,
      0.16394999999999998,
      0.16394999999999998,
      0.20124999999999998,
      0.20124999999999998,
      0.20124999999999998,
      0.21315,
      0.21315,
      0.21315,
      0.20105,
      0.20105,
      0.20105,
      0.1872,
      0.1872,
      0.1872,
      0.21084999999999998,
      0.21084999999999998,
      0.21084999999999998,
      0.22215000000000001,
      0.22215000000000001,
      0.22215000000000001,
      0.2202,
      0.2202,
      0.2202,
      0.21915,
      0.21915,
      0.21915,
      0.18364999999999998,
      0.18364999999999998,
      0.18364999999999998,
      0.19745000000000001,
      0.19745000000000001,
      0.19745000000000001,
      0.22954999999999998,
      0.22954999999999998,
      0.22954999999999998,
      0.20065,
      0.20065,
      0.20065,
      0.2272,
      0.2272,
      0.2272,
      0.19845000000000002,
      0.19845000000000002,
      0.19845000000000002,
      0.2205,
      0.2205,
      0.2205,
      0.23585,
      0.23585,
      0.23585,
      0.21205,
      0.21205,
      0.21205,
      0.21845,
      0.21845,
      0.21845,
      0.2338,
      0.2338,
      0.2338,
      0.2244,
      0.2244,
      0.2244,
      0.15635,
      0.15635,
      0.15635,
      0.2143,
      0.2143,
      0.2143,
      0.2242,
      0.2242,
      0.2242,
      0.21745,
      0.21745,
      0.21745,
      0.21439999999999998,
      0.21439999999999998,
      0.21439999999999998,
      0.20885,
      0.20885,
      0.20885,
      0.226,
      0.226,
      0.226,
      0.2153,
      0.2153,
      0.2153,
      0.20525,
      0.20525,
      0.20525,
      0.224,
      0.224,
      0.224,
      0.22885,
      0.22885,
      0.22885,
      0.20989999999999998,
      0.20989999999999998,
      0.20989999999999998,
      0.2172,
      0.2172,
      0.2172,
      0.201,
      0.201,
      0.201,
      0.19674999999999998,
      0.19674999999999998,
      0.19674999999999998,
      0.2092,
      0.2092,
      0.2092,
      0.2062,
      0.2062,
      0.2062,
      0.2208,
      0.2208,
      0.2208,
      0.22335,
      0.22335,
      0.22335,
      0.20655,
      0.20655,
      0.20655,
      0.20224999999999999,
      0.20224999999999999,
      0.20224999999999999,
      0.23255,
      0.23255,
      0.23255,
      0.22235,
      0.22235,
      0.22235,
      0.2289,
      0.2289,
      0.2289,
      0.2361,
      0.2361,
      0.2361,
      0.22935,
      0.22935,
      0.22935,
      0.2253,
      0.2253,
      0.2253,
      0.2046,
      0.2046,
      0.2046,
      0.22655,
      0.22655,
      0.22655,
      0.21975,
      0.21975,
      0.21975,
      0.23745,
      0.23745,
      0.23745,
      0.24769999999999998,
      0.24769999999999998,
      0.24769999999999998,
      0.23305,
      0.23305,
      0.23305,
      0.2352,
      0.2352,
      0.2352,
      0.21855,
      0.21855,
      0.21855,
      0.21639999999999998,
      0.21639999999999998,
      0.21639999999999998,
      0.2177,
      0.2177,
      0.2177,
      0.19355,
      0.19355,
      0.19355,
      0.21835,
      0.21835,
      0.21835,
      0.22544999999999998,
      0.22544999999999998,
      0.22544999999999998,
      0.21939999999999998,
      0.21939999999999998,
      0.21939999999999998,
      0.21889999999999998,
      0.21889999999999998,
      0.21889999999999998,
      0.2101,
      0.2101,
      0.2101,
      0.20415,
      0.20415,
      0.20415,
      0.21915,
      0.21915,
      0.21915,
      0.2136,
      0.2136,
      0.2136,
      0.22249999999999998,
      0.22249999999999998,
      0.22249999999999998,
      0.2238,
      0.2238,
      0.2238,
      0.19765,
      0.19765,
      0.19765,
      0.21205,
      0.21205,
      0.21205,
      0.22705,
      0.22705,
      0.22705,
      0.2228,
      0.2228,
      0.2228,
      0.19324999999999998,
      0.19324999999999998,
      0.19324999999999998,
      0.19455,
      0.19455,
      0.19455,
      0.21239999999999998,
      0.21239999999999998,
      0.21239999999999998,
      0.1862,
      0.1862,
      0.1862,
      0.21595,
      0.21595,
      0.21595,
      0.21985,
      0.21985,
      0.21985,
      0.2115,
      0.2115,
      0.2115,
      0.2144,
      0.2144,
      0.2144,
      0.1958,
      0.1958,
      0.1958,
      0.20535,
      0.20535,
      0.20535,
      0.21989999999999998,
      0.21989999999999998,
      0.21989999999999998,
      0.1975,
      0.1975,
      0.1975,
      0.227,
      0.227,
      0.227,
      0.20800000000000002,
      0.20800000000000002,
      0.20800000000000002,
      0.20995000000000003,
      0.20995000000000003,
      0.20995000000000003,
      0.187,
      0.187,
      0.187,
      0.2145,
      0.2145,
      0.2145,
      0.21165,
      0.21165,
      0.21165,
      0.21495,
      0.21495,
      0.21495,
      0.23445,
      0.23445,
      0.23445,
      0.2136,
      0.2136,
      0.2136,
      0.22175,
      0.22175,
      0.22175,
      0.21484999999999999,
      0.21484999999999999,
      0.21484999999999999,
      0.20665,
      0.20665,
      0.20665,
      0.22044999999999998,
      0.22044999999999998,
      0.22044999999999998,
      0.2015,
      0.2015,
      0.2015,
      0.22260000000000002,
      0.22260000000000002,
      0.22260000000000002,
      0.224,
      0.224,
      0.224,
      0.21660000000000001,
      0.21660000000000001,
      0.21660000000000001,
      0.22,
      0.22,
      0.22,
      0.2059,
      0.2059,
      0.2059,
      0.189,
      0.189,
      0.189,
      0.18445,
      0.18445,
      0.18445,
      0.1951,
      0.1951,
      0.1951,
      0.21545,
      0.21545,
      0.21545,
      0.2164,
      0.2164,
      0.2164,
      0.20834999999999998,
      0.20834999999999998,
      0.20834999999999998,
      0.20655,
      0.20655,
      0.20655,
      0.20989999999999998,
      0.20989999999999998,
      0.20989999999999998,
      0.20074999999999998,
      0.20074999999999998,
      0.20074999999999998,
      0.16815,
      0.16815,
      0.16815,
      0.18675,
      0.18675,
      0.18675,
      0.1966,
      0.1966,
      0.1966,
      0.19705,
      0.19705,
      0.19705,
      0.20305,
      0.20305,
      0.20305,
      0.19690000000000002,
      0.19690000000000002,
      0.19690000000000002,
      0.2122,
      0.2122,
      0.2122,
      0.17195,
      0.17195,
      0.17195
    ],
    "latency": [
      298.04677928455453,
      1497.3080758474662,
      356.142955881351,
      805.6480287226259,
      733.8400554238417,
      1460.041805573277,
      3809.5189925351006,
      484.07463854554885,
      567.3849522369169,
      340.9850467624282,
      597.9103476732674,
      1891.100333542127,
      1231.084448689997,
      2799.6259463437873,
      218.83617614097327,
      454.61421410882,
      2090.2231258061615,
      7306.673311959812,
      659.623591755851,
      1482.4112123972536,
      1224.808800801283,
      1108.0699681489725,
      298.32025387727253,
      7184.372463680597,
      201.77957607639712,
      354.84469009099087,
      570.6723290304965,
      10181.687370607446,
      470.4641617580312,
      443.55646489321384,
      949.8329394816155,
      807.4260358695745,
      265.7607727386055,
      242.22188422292288,
      398.1147994298108,
      880.0574495176913,
      899.1503644625393,
      566.8704007254744,
      3689.580248222732,
      8985.50611519027,
      32696.494158788108,
      696.794244598223,
      473.51654144707356,
      611.4427398712887,
      225.55535085463708,
      1366.7401193736544,
      386.3740435061493,
      5361.66286356665,
      149.29705224774426,
      2968.1145537180296,
      398.6135712439961,
      741.5843462738678,
      741.8571341420702,
      330.52522212139877,
      1312.6701186100288,
      584.3020155758834,
      228.29569337242094,
      2800.0260388053975,
      570.5922517556539,
      2473.386042762795,
      394.9972750531238,
      503.9912767752471,
      188.65607153533168,
      1197.1240382453407,
      671.6316712967669,
      428.7779839414718,
      981.4905079270029,
      314.7674267009934,
      659.1331692088751,
      323.9118971250206,
      1032.7516097633625,
      559.295656619282,
      6796.154458199808,
      2981.737392096714,
      735.0104263056967,
      1113.0368686521301,
      461.2658314837396,
      1549.5485817200667,
      7954.202700232253,
      2652.3933863050597,
      248.08213946779756,
      2521.0677973991587,
      14257.052397799705,
      5902.792102551404,
      2521.543823545133,
      676.8313699236635,
      1473.6502615132554,
      210.95218245181727,
      794.4998436999535,
      807.6168141789983,
      252.81700183904667,
      444.06097211522007,
      720.4530151424481,
      18446.05490394791,
      223.5020272748509,
      484.1769489405865,
      1588.9103584833301,
      669.3774825274841,
      657.8279496933304,
      1704.9441027844807,
      345.34033346284855,
      257.68584677219036,
      401.522100672541,
      1543.2334683563045,
      647.7286503989787,
      205.63549748063548,
      227.07774749357614,
      455.98021232551105,
      13000.145175556858,
      476.44574504111665,
      238.81326173218804,
      450.46874300634806,
      210.71754678067606,
      2618.6375835941244,
      465.4159486085059,
      316.1798690781171,
      178.9645551691956,
      449.11721874453053,
      228.34694194871463,
      369.69020619033876,
      612.6322224870559,
      658.3348009038524,
      412.1878913875887,
      1024.9912447506833,
      270.89246398390776,
      363.8804968387204,
      349.2770123460506,
      468.32256166278444,
      1584.3084505934291,
      402.58042731571703,
      198.98452566848943,
      536.5736845355378,
      639.7621234241062,
      309.6091947643804,
      347.943324021421,
      598.0140532542586,
      186.90437618891644,
      819.7298303872913,
      698.5520024862236,
      1354.2515979326058,
      917.6973504428255,
      916.8594776181901,
      294.90783414855343,
      332.84414432186327,
      6299.736210934734,
      1142.300346449706,
      592.8461856778335,
      9375.705180804776,
      1354.4697451229824,
      568.0588081215452,
      3143.106839916949,
      718.6978856931538,
      721.0604323888706,
      10586.228356032148,
      537.787746369412,
      747.0507604130028,
      640.2375538299251,
      615.3256047150821,
      4715.675351119503,
      678.7505031316239,
      4815.101016745257,
      238.75682306151072,
      4738.331478931148,
      3632.9344316617553,
      405.16367879806603,
      125.40569005630763,
      388.66095841168044,
      560.6606876988906,
      270.41617921533975,
      694.6804590471685,
      307.85647476223596,
      2047.8202803215263,
      6211.593970823899,
      10556.905304354184,
      1912.8746991173182,
      2806.4232331994285,
      288.6994244198551,
      2626.4395424704035,
      390.77992037781615,
      472.41133384460636,
      1134.8127064194578,
      249.33858406927416,
      466.29209059830714,
      310.37539294344384,
      268.0589971608388,
      218.8366891432479,
      20092.70070466121,
      1020.7668272145439,
      188.37824454768122,
      598.8897412829434,
      415.19659512467103,
      476.610006657853,
      374.69075998623146,
      565.2786713644543,
      298.39064745238227,
      5324.277388064664,
      782.2818875933028,
      315.37793902356316,
      2298.2063608664876,
      507.13236506102845,
      1696.5292478587453,
      313.3817628603898,
      271.7259858504908,
      1066.024425857313,
      205.11812526667342,
      414.7860185228134,
      395.1348811226246,
      13423.19303612972,
      4167.154220529278,
      460.32389634596916,
      1295.2964646892492,
      1063.161350582896,
      489.5175495157665,
      3932.641033922221,
      534.92623122616,
      369.97402961358694,
      560.0038417012755,
      346.03579434068786,
      923.5831287521075,
      259.04584395096214,
      496.188128717646,
      18883.057380068843,
      851.3255142047295,
      4469.940595372072,
      279.6900872881182,
      255.58918782680237,
      512.3798154293897,
      2055.2805254724285,
      357.40108738735836,
      460.4825676923142,
      508.6801882274541,
      345.4112900348918,
      844.0910478855532,
      283.3172707428023,
      5868.913210386701,
      1064.9334387012345,
      224.8713893038809,
      740.065694704934,
      971.9280564787725,
      1274.4691355383518,
      329.31106347002225,
      180.99726881983352,
      480.2341702893213,
      12537.462892033041,
      198.94811523668008,
      768.317517139632,
      2868.476657282029,
      161.18795796516096,
      7038.293313248909,
      1441.525702485963,
      972.5449325079135,
      201.8824507216449,
      275.19119214229477,
      273.2296774071548,
      2843.5680160163333,
      2983.5688457462247,
      2689.4603285575267,
      10342.67392341147,
      1759.0577029278052,
      214.7984194660823,
      1612.328399409167,
      466.32103252827017,
      571.0383924653423,
      10675.937464284796,
      334.85512844429223,
      547.9289530699144,
      4718.001780879475,
      6865.526581767656,
      189.5925474911432,
      891.96605948615,
      3720.254992313642,
      439.2587453987493,
      2579.895425818924,
      1136.887734052539,
      342.2056153779599,
      641.4336540591753,
      480.80835696437896,
      1670.5446017388613,
      2869.0346081866483,
      582.6680023058996,
      334.2490738084697,
      238.4804836277522,
      998.1060075690823,
      1170.6925486761218,
      514.665527775,
      376.22829666276317,
      1444.9127587908815,
      500.118710362224,
      1237.0573039174822,
      299.7842094643155,
      10722.142014547886,
      986.748711853578,
      408.0566415792189,
      293.1129134118356,
      758.0269096858664,
      263.2477416873546,
      286.29287954465946,
      481.6099147791137,
      1195.6774060234106,
      630.7387058400443,
      413.8528503211533,
      1584.3448669558443,
      625.4992520095609,
      2968.0681214757733,
      615.832543488203,
      353.37616922849367,
      1975.9862818689567,
      3221.716527846542,
      2866.254761978083,
      590.915334001443,
      272.93758974919933,
      486.16430329903847,
      691.494928172553,
      805.3790831198074,
      197.86397690505066,
      304.6518548435136,
      359.6594644319527,
      771.2504702185933,
      941.3946140960525,
      475.97122427183547,
      347.696234952641,
      531.087478594166,
      423.60000142188755,
      218.92141764603062,
      586.1603325209395,
      465.2187134518391,
      756.1393659588462,
      1203.5119641420856,
      383.4770835519636,
      1017.3059924915984,
      1299.6943865239473,
      10266.994534164724,
      764.6545850896323,
      1118.6342560209832,
      2201.460554635232,
      3352.951908793043,
      1571.7489738848365,
      498.05850844338556,
      556.9481904888884,
      455.32031960685094,
      239.27615734603296,
      15399.333168752079,
      316.5841337538527,
      776.318046086799,
      547.560333314701,
      609.3417502946357,
      420.41670910805794,
      260.80735895256186,
      1720.7972736075876,
      423.1767364844923,
      572.6209167789088,
      855.7132039745746,
      261.778430158297,
      1434.3703907015313,
      820.8970116846051,
      1174.0140400648506,
      813.2751272498409,
      651.249881816427,
      347.003506244512,
      455.75222952657566,
      276.44160539033686,
      1131.389949188873,
      192.21099629040017,
      314.42470474091226,
      843.422886888372,
      350.47922410080395,
      312.8290349636228,
      267.86231792768206,
      246.2280588264481,
      302.6359776398127,
      1365.0351464858088,
      902.7625816773088,
      1678.5769714738076,
      712.7686520702207,
      653.3299260192381,
      416.2602309284983,
      727.1595146039213,
      1601.8036303789147,
      2803.5055099982565,
      182.8635955889809,
      1400.070074966435,
      214.5731140884642,
      1062.69496771264,
      299.6877395840321,
      433.2848346871072,
      1150.350340982776,
      719.3706367011005,
      2233.645657811382,
      299.173476807736,
      399.00622613171856,
      445.95559113809253,
      407.5421100439486,
      297.1982203053991,
      2420.5249327134793,
      1469.927973111542,
      504.3194323574032,
      581.1529231646273,
      593.6718463676663,
      276.6440973755046,
      1720.4013033488507,
      372.55985990320914,
      476.5875741406946,
      505.5206204182751,
      213.8928320988261,
      1578.2787665196297,
      492.75613111021994,
      249.04923805333794,
      384.8899839280476,
      505.0689133466358,
      305.26166451736464,
      16802.11593696936,
      668.1943269778731,
      2304.13993050914,
      605.9400890645672,
      2342.875709463441,
      505.521493067289,
      1082.5907565741038,
      191.17716200900782,
      261.52471996548934,
      608.1096473065687,
      921.4294707734352,
      1045.8839316370907,
      1488.273734128008,
      377.1981080651686,
      624.1860950799518,
      8178.17984413251,
      135.846572038754,
      291.63183880585734,
      429.78419536516355,
      2069.6181442018105,
      268.29331318884687,
      598.5648933831385,
      2135.343463196022,
      4436.939970976123,
      449.70307982875966,
      9356.467288098407,
      860.2808365790474,
      724.2324203771316,
      321.8992438813889,
      244.18630888543183,
      1120.565006626687,
      1192.6196582514206,
      177.15877243352256,
      760.8715318155428,
      4516.865170622243,
      195.2960099996259,
      554.7297558243731,
      936.712141743423,
      2155.884010108099,
      6301.798642321039,
      340.9308765593063,
      543.0520002295204,
      334.02210300875925,
      1119.249493044354,
      295.699205098538,
      390.4736168288581,
      1228.62738560639,
      405.91132045268614,
      540.3503951212554,
      990.1895123048378,
      1183.1024772511935,
      295.4722537159345,
      534.7518299708522,
      762.4677668753263,
      162.65418939554723,
      1404.8676251280824,
      4846.794395422841,
      1375.386999121972,
      1143.8776412119967,
      591.3993978740895,
      481.391566234063,
      851.4558582271333,
      562.0387078168746,
      23422.03855688544,
      653.5564692037012,
      291.75552830666254,
      2173.089627806353,
      347.17125841867414,
      390.73305471469234,
      496.0332254357764,
      620.6172284529125,
      938.6944536903045,
      386.9369651206634,
      237.5753463290787,
      516.0234454563574,
      500.9723100012835,
      563.4262476649371,
      485.74473084013744,
      693.1799168251946,
      2354.263994351927,
      536.7864601784669,
      176.77022378471867,
      145.10753434730194,
      736.8963126840889,
      3163.1139024855484,
      16636.002725209626,
      1309.5641918289107,
      10720.251853616955,
      587.6459580329557,
      14244.939421530113
    ],
    "latency_median": 484.3159594678873,
    "weight_divergence": [
      0.0,
      0.0,
      10.061436653137207,
      10.061436653137207,
      10.061436653137207,
      9.191423416137695,
      9.191423416137695,
      9.191423416137695,
      8.964566707611084,
      8.964566707611084,
      8.964566707611084,
      8.60875940322876,
      8.60875940322876,
      8.60875940322876,
      8.151487827301025,
      8.151487827301025,
      8.151487827301025,
      39.63227844238281,
      39.63227844238281,
      39.63227844238281,
      60.95183563232422,
      60.95183563232422,
      60.95183563232422,
      57.993635177612305,
      57.993635177612305,
      57.993635177612305,
      52.55515480041504,
      52.55515480041504,
      52.55515480041504,
      47.783884048461914,
      47.783884048461914,
      47.783884048461914,
      41.23043441772461,
      41.23043441772461,
      41.23043441772461,
      35.67941856384277,
      35.67941856384277,
      35.67941856384277,
      30.34096050262451,
      30.34096050262451,
      30.34096050262451,
      28.361522674560547,
      28.361522674560547,
      28.361522674560547,
      25.779544830322266,
      25.779544830322266,
      25.779544830322266,
      23.456048011779785,
      23.456048011779785,
      23.456048011779785,
      24.0442533493042,
      24.0442533493042,
      24.0442533493042,
      22.89313793182373,
      22.89313793182373,
      22.89313793182373,
      23.02430248260498,
      23.02430248260498,
      23.02430248260498,
      20.79354190826416,
      20.79354190826416,
      20.79354190826416,
      20.947586059570312,
      20.947586059570312,
      20.947586059570312,
      20.6902437210083,
      20.6902437210083,
      20.6902437210083,
      21.355993270874023,
      21.355993270874023,
      21.355993270874023,
      20.995203018188477,
      20.995203018188477,
      20.995203018188477,
      19.911231994628906,
      19.911231994628906,
      19.911231994628906,
      21.05470561981201,
      21.05470561981201,
      21.05470561981201,
      18.838997840881348,
      18.838997840881348,
      18.838997840881348,
      19.110697746276855,
      19.110697746276855,
      19.110697746276855,
      17.65054988861084,
      17.65054988861084,
      17.65054988861084,
      17.873957633972168,
      17.873957633972168,
      17.873957633972168,
      20.242704391479492,
      20.242704391479492,
      20.242704391479492,
      18.65359401702881,
      18.65359401702881,
      18.65359401702881,
      20.73116397857666,
      20.73116397857666,
      20.73116397857666,
      19.17448616027832,
      19.17448616027832,
      19.17448616027832,
      16.84071445465088,
      16.84071445465088,
      16.84071445465088,
      18.695615768432617,
      18.695615768432617,
      18.695615768432617,
      20.276758193969727,
      20.276758193969727,
      20.276758193969727,
      20.607513427734375,
      20.607513427734375,
      20.607513427734375,
      20.489490509033203,
      20.489490509033203,
      20.489490509033203,
      18.78513813018799,
      18.78513813018799,
      18.78513813018799,
      18.7232084274292,
      18.7232084274292,
      18.7232084274292,
      21.08957004547119,
      21.08957004547119,
      21.08957004547119,
      25.694734573364258,
      25.694734573364258,
      25.694734573364258,
      21.971028327941895,
      21.971028327941895,
      21.971028327941895,
      21.054264068603516,
      21.054264068603516,
      21.054264068603516,
      20.73746967315674,
      20.73746967315674,
      20.73746967315674,
      20.84918975830078,
      20.84918975830078,
      20.84918975830078,
      22.439764976501465,
      22.439764976501465,
      22.439764976501465,
      21.261332511901855,
      21.261332511901855,
      21.261332511901855,
      19.1278133392334,
      19.1278133392334,
      19.1278133392334,
      21.19154453277588,
      21.19154453277588,
      21.19154453277588,
      19.992645263671875,
      19.992645263671875,
      19.992645263671875,
      18.64486789703369,
      18.64486789703369,
      18.64486789703369,
      21.991084098815918,
      21.991084098815918,
      21.991084098815918,
      21.72246551513672,
      21.72246551513672,
      21.72246551513672,
      21.196924209594727,
      21.196924209594727,
      21.196924209594727,
      20.740147590637207,
      20.740147590637207,
      20.740147590637207,
      20.591208457946777,
      20.591208457946777,
      20.591208457946777,
      18.791312217712402,
      18.791312217712402,
      18.791312217712402,
      19.20322322845459,
      19.20322322845459,
      19.20322322845459,
      18.61405372619629,
      18.61405372619629,
      18.61405372619629,
      17.207557678222656,
      17.207557678222656,
      17.207557678222656,
      19.9714298248291,
      19.9714298248291,
      19.9714298248291,
      17.26358699798584,
      17.26358699798584,
      17.26358699798584,
      20.981109619140625,
      20.981109619140625,
      20.981109619140625,
      21.409473419189453,
      21.409473419189453,
      21.409473419189453,
      17.88157367706299,
      17.88157367706299,
      17.88157367706299,
      20.15102481842041,
      20.15102481842041,
      20.15102481842041,
      17.699332237243652,
      17.699332237243652,
      17.699332237243652,
      17.756415367126465,
      17.756415367126465,
      17.756415367126465,
      18.856528282165527,
      18.856528282165527,
      18.856528282165527,
      19.708629608154297,
      19.708629608154297,
      19.708629608154297,
      19.94606304168701,
      19.94606304168701,
      19.94606304168701,
      20.352829933166504,
      20.352829933166504,
      20.352829933166504,
      17.300415992736816,
      17.300415992736816,
      17.300415992736816,
      20.576379776000977,
      20.576379776000977,
      20.576379776000977,
      18.031912803649902,
      18.031912803649902,
      18.031912803649902,
      19.03614044189453,
      19.03614044189453,
      19.03614044189453,
      18.153337478637695,
      18.153337478637695,
      18.153337478637695,
      16.273555278778076,
      16.273555278778076,
      16.273555278778076,
      16.600133895874023,
      16.600133895874023,
      16.600133895874023,
      18.043423652648926,
      18.043423652648926,
      18.043423652648926,
      17.069875717163086,
      17.069875717163086,
      17.069875717163086,
      17.08329677581787,
      17.08329677581787,
      17.08329677581787,
      18.393718719482422,
      18.393718719482422,
      18.393718719482422,
      17.370835304260254,
      17.370835304260254,
      17.370835304260254,
      17.99741268157959,
      17.99741268157959,
      17.99741268157959,
      15.64881944656372,
      15.64881944656372,
      15.64881944656372,
      16.910095691680908,
      16.910095691680908,
      16.910095691680908,
      17.169374465942383,
      17.169374465942383,
      17.169374465942383,
      16.797547817230225,
      16.797547817230225,
      16.797547817230225,
      16.91947650909424,
      16.91947650909424,
      16.91947650909424,
      17.001670837402344,
      17.001670837402344,
      17.001670837402344,
      17.95732831954956,
      17.95732831954956,
      17.95732831954956,
      14.972125053405762,
      14.972125053405762,
      14.972125053405762,
      16.603946208953857,
      16.603946208953857,
      16.603946208953857,
      17.59667682647705,
      17.59667682647705,
      17.59667682647705,
      15.510603904724121,
      15.510603904724121,
      15.510603904724121,
      17.914851188659668,
      17.914851188659668,
      17.914851188659668,
      15.390854835510254,
      15.390854835510254,
      15.390854835510254,
      20.29899501800537,
      20.29899501800537,
      20.29899501800537,
      17.91062641143799,
      17.91062641143799,
      17.91062641143799,
      16.554890155792236,
      16.554890155792236,
      16.554890155792236,
      18.847686767578125,
      18.847686767578125,
      18.847686767578125,
      17.827326774597168,
      17.827326774597168,
      17.827326774597168,
      16.134793758392334,
      16.134793758392334,
      16.134793758392334,
      17.787915229797363,
      17.787915229797363,
      17.787915229797363,
      16.582021713256836,
      16.582021713256836,
      16.582021713256836,
      17.70765209197998,
      17.70765209197998,
      17.70765209197998,
      17.96304750442505,
      17.96304750442505,
      17.96304750442505,
      16.727505207061768,
      16.727505207061768,
      16.727505207061768,
      16.37111473083496,
      16.37111473083496,
      16.37111473083496,
      17.36805248260498,
      17.36805248260498,
      17.36805248260498,
      16.00802755355835,
      16.00802755355835,
      16.00802755355835,
      20.694272994995117,
      20.694272994995117,
      20.694272994995117,
      15.627048015594482,
      15.627048015594482,
      15.627048015594482,
      15.812435150146484,
      15.812435150146484,
      15.812435150146484,
      18.033294677734375,
      18.033294677734375,
      18.033294677734375,
      21.291311264038086,
      21.291311264038086,
      21.291311264038086,
      20.494667053222656,
      20.494667053222656,
      20.494667053222656,
      16.27790880203247,
      16.27790880203247,
      16.27790880203247,
      26.11667537689209,
      26.11667537689209,
      26.11667537689209,
      15.794328212738037,
      15.794328212738037,
      15.794328212738037,
      13.49839973449707,
      13.49839973449707,
      13.49839973449707,
      14.509653091430664,
      14.509653091430664,
      14.509653091430664,
      16.121381282806396,
      16.121381282806396,
      16.121381282806396,
      15.786071300506592,
      15.786071300506592,
      15.786071300506592,
      19.954145908355713,
      19.954145908355713,
      19.954145908355713,
      13.2587890625,
      13.2587890625,
      13.2587890625,
      19.555620193481445,
      19.555620193481445,
      19.555620193481445,
      13.577498435974121,
      13.577498435974121,
      13.577498435974121,
      16.39234209060669,
      16.39234209060669,
      16.39234209060669,
      16.467281818389893,
      16.467281818389893,
      16.467281818389893,
      16.874074935913086,
      16.874074935913086,
      16.874074935913086,
      15.107377529144287,
      15.107377529144287,
      15.107377529144287,
      15.014391422271729,
      15.014391422271729,
      15.014391422271729,
      15.323698997497559,
      15.323698997497559,
      15.323698997497559,
      15.089245796203613,
      15.089245796203613,
      15.089245796203613,
      13.891005516052246,
      13.891005516052246,
      13.891005516052246,
      16.07674217224121,
      16.07674217224121,
      16.07674217224121,
      15.148784637451172,
      15.148784637451172,
      15.148784637451172,
      14.551244258880615,
      14.551244258880615,
      14.551244258880615,
      15.070494651794434,
      15.070494651794434,
      15.070494651794434,
      19.337110996246338,
      19.337110996246338,
      19.337110996246338,
      14.050600051879883,
      14.050600051879883,
      14.050600051879883,
      12.230453968048096,
      12.230453968048096,
      12.230453968048096,
      15.616410732269287,
      15.616410732269287,
      15.616410732269287,
      14.37641954421997,
      14.37641954421997,
      14.37641954421997,
      17.125941276550293,
      17.125941276550293,
      17.125941276550293,
      21.778742790222168,
      21.778742790222168,
      21.778742790222168,
      20.604763984680176,
      20.604763984680176,
      20.604763984680176,
      15.645648956298828,
      15.645648956298828,
      15.645648956298828,
      13.627849578857422,
      13.627849578857422,
      13.627849578857422,
      16.438379287719727,
      16.438379287719727,
      16.438379287719727,
      17.622041702270508,
      17.622041702270508,
      17.622041702270508,
      15.931157112121582,
      15.931157112121582,
      15.931157112121582,
      42.209022521972656,
      42.209022521972656,
      42.209022521972656,
      16.256330966949463,
      16.256330966949463,
      16.256330966949463,
      28.575600624084473,
      28.575600624084473,
      28.575600624084473,
      16.992395401000977,
      16.992395401000977,
      16.992395401000977,
      13.541011333465576,
      13.541011333465576,
      13.541011333465576,
      14.460707664489746,
      14.460707664489746,
      14.460707664489746,
      15.156644821166992,
      15.156644821166992,
      15.156644821166992,
      16.467073440551758,
      16.467073440551758,
      16.467073440551758,
      16.421656608581543,
      16.421656608581543,
      16.421656608581543,
      21.718730926513672,
      21.718730926513672,
      21.718730926513672
    ]
  }
}