{
  "config": {
    "client_algorithm": "sgd",
    "client_batch_size": 32,
    "client_lr": 0.01,
    "client_n_epochs": 4,
    "client_selection_fraction": 0.3,
    "clients_distribution": "balanced",
    "clients_mobility": true,
    "dataset_distribution": "non_iid",
    "dataset_name": "mnist",
    "debug": false,
    "epochs_delay_localSGD": 10,
    "log_frequency": 1,
    "log_verbosity": 2,
    "lr_warmup": false,
    "mobility_rate": 0.5,
    "model_init": "random",
    "model_type": "mnist",
    "move_to_neighbours": false,
    "n_clients": 250,
    "n_clusters": 25,
    "server_global_rate": 7,
    "stdout_frequency": 1,
    "stdout_verbosity": 2,
    "stop_condition": "rounds",
    "stop_value": 250,
    "log_file": "log_files/mnist_non_iid_postlocal_extra-47"
  },
  "results": {
    "rounds": [
      1,
      2,
      3,
      4,
      5,
      6,
      7,
      8,
      9,
      10,
      11,
      12,
      13,
      14,
      15,
      16,
      17,
      18,
      19,
      20,
      21,
      22,
      23,
      24,
      25,
      26,
      27,
      28,
      29,
      30,
      31,
      32,
      33,
      34,
      35,
      36,
      37,
      38,
      39,
      40,
      41,
      42,
      43,
      44,
      45,
      46,
      47,
      48,
      49,
      50,
      51,
      52,
      53,
      54,
      55,
      56,
      57,
      58,
      59,
      60,
      61,
      62,
      63,
      64,
      65,
      66,
      67,
      68,
      69,
      70,
      71,
      72,
      73,
      74,
      75,
      76,
      77,
      78,
      79,
      80,
      81,
      82,
      83,
      84,
      85,
      86,
      87,
      88,
      89,
      90,
      91,
      92,
      93,
      94,
      95,
      96,
      97,
      98,
      99,
      100,
      101,
      102,
      103,
      104,
      105,
      106,
      107,
      108,
      109,
      110,
      111,
      112,
      113,
      114,
      115,
      116,
      117,
      118,
      119,
      120,
      121,
      122,
      123,
      124,
      125,
      126,
      127,
      128,
      129,
      130,
      131,
      132,
      133,
      134,
      135,
      136,
      137,
      138,
      139,
      140,
      141,
      142,
      143,
      144,
      145,
      146,
      147,
      148,
      149,
      150,
      151,
      152,
      153,
      154,
      155,
      156,
      157,
      158,
      159,
      160,
      161,
      162,
      163,
      164,
      165,
      166,
      167,
      168,
      169,
      170,
      171,
      172,
      173,
      174,
      175,
      176,
      177,
      178,
      179,
      180,
      181,
      182,
      183,
      184,
      185,
      186,
      187,
      188,
      189,
      190,
      191,
      192,
      193,
      194,
      195,
      196,
      197,
      198,
      199,
      200,
      201,
      202,
      203,
      204,
      205,
      206,
      207,
      208,
      209,
      210,
      211,
      212,
      213,
      214,
      215,
      216,
      217,
      218,
      219,
      220,
      221,
      222,
      223,
      224,
      225,
      226,
      227,
      228,
      229,
      230,
      231,
      232,
      233,
      234,
      235,
      236,
      237,
      238,
      239,
      240,
      241,
      242,
      243,
      244,
      245,
      246,
      247,
      248,
      249,
      250
    ],
    "train_accuracy": [
      0.0,
      0.0,
      0.0,
      0.0,
      0.0,
      0.0,
      0.0,
      0.0,
      0.0,
      0.0,
      0.0,
      0.0,
      0.0,
      0.0,
      0.0,
      0.0,
      0.0,
      0.0,
      0.0,
      0.0,
      0.0,
      0.0,
      0.0,
      0.0,
      0.0,
      0.0,
      0.0,
      0.0,
      0.0,
      0.0,
      0.0,
      0.0,
      0.0,
      0.0,
      0.0,
      0.0,
      0.0,
      0.0,
      0.0,
      0.0,
      0.0,
      0.0,
      0.0,
      0.0,
      0.0,
      0.0,
      0.0,
      0.0,
      0.0,
      0.0,
      0.0,
      0.0,
      0.0,
      0.0,
      0.0,
      0.0,
      0.0,
      0.0,
      0.0,
      0.0,
      0.0,
      0.0,
      0.0,
      0.0,
      0.0,
      0.0,
      0.0,
      0.0,
      0.0,
      0.0,
      0.0,
      0.0,
      0.0,
      0.0,
      0.0,
      0.0,
      0.0,
      0.0,
      0.0,
      0.0,
      0.0,
      0.0,
      0.0,
      0.0,
      0.0,
      0.0,
      0.0,
      0.0,
      0.0,
      0.0,
      0.0,
      0.0,
      0.0,
      0.0,
      0.0,
      0.0,
      0.0,
      0.0,
      0.0,
      0.0,
      0.0,
      0.0,
      0.0,
      0.0,
      0.0,
      0.0,
      0.0,
      0.0,
      0.0,
      0.0,
      0.0,
      0.0,
      0.0,
      0.0,
      0.0,
      0.0,
      0.0,
      0.0,
      0.0,
      0.0,
      0.0,
      0.0,
      0.0,
      0.0,
      0.0,
      0.0,
      0.0,
      0.0,
      0.0,
      0.0,
      0.0,
      0.0,
      0.0,
      0.0,
      0.0,
      0.0,
      0.0,
      0.0,
      0.0,
      0.0,
      0.0,
      0.0,
      0.0,
      0.0,
      0.0,
      0.0,
      0.0,
      0.0,
      0.0,
      0.0,
      0.0,
      0.0,
      0.0,
      0.0,
      0.0,
      0.0,
      0.0,
      0.0,
      0.0,
      0.0,
      0.0,
      0.0,
      0.0,
      0.0,
      0.0,
      0.0,
      0.0,
      0.0,
      0.0,
      0.0,
      0.0,
      0.0,
      0.0,
      0.0,
      0.0,
      0.0,
      0.0,
      0.0,
      0.0,
      0.0,
      0.0,
      0.0,
      0.0,
      0.0,
      0.0,
      0.0,
      0.0,
      0.0,
      0.0,
      0.0,
      0.0,
      0.0,
      0.0,
      0.0,
      0.0,
      0.0,
      0.0,
      0.0,
      0.0,
      0.0,
      0.0,
      0.0,
      0.0,
      0.0,
      0.0,
      0.0,
      0.0,
      0.0,
      0.0,
      0.0,
      0.0,
      0.0,
      0.0,
      0.0,
      0.0,
      0.0,
      0.0,
      0.0,
      0.0,
      0.0,
      0.0,
      0.0,
      0.0,
      0.0,
      0.0,
      0.0,
      0.0,
      0.0,
      0.0,
      0.0,
      0.0,
      0.0,
      0.0,
      0.0,
      0.0,
      0.0,
      0.0,
      0.0,
      0.0,
      0.0,
      0.0,
      0.0,
      0.0,
      0.0,
      0.0,
      0.0,
      0.0,
      0.0,
      0.0,
      0.0
    ],
    "test_accuracy": [
      0.0,
      0.0,
      0.0,
      0.0,
      0.0,
      0.0,
      0.3836428571428572,
      0.3836428571428572,
      0.3836428571428572,
      0.3836428571428572,
      0.3836428571428572,
      0.3836428571428572,
      0.3836428571428572,
      0.5989285714285715,
      0.5989285714285715,
      0.5989285714285715,
      0.5989285714285715,
      0.5989285714285715,
      0.5989285714285715,
      0.5989285714285715,
      0.7089857142857142,
      0.7089857142857142,
      0.7089857142857142,
      0.7089857142857142,
      0.7089857142857142,
      0.7089857142857142,
      0.7089857142857142,
      0.7398428571428571,
      0.7398428571428571,
      0.7398428571428571,
      0.7398428571428571,
      0.7398428571428571,
      0.7398428571428571,
      0.7398428571428571,
      0.7594428571428571,
      0.7594428571428571,
      0.7594428571428571,
      0.7594428571428571,
      0.7594428571428571,
      0.7594428571428571,
      0.7594428571428571,
      0.7884285714285713,
      0.7884285714285713,
      0.7884285714285713,
      0.7884285714285713,
      0.7884285714285713,
      0.7884285714285713,
      0.7884285714285713,
      0.8254571428571428,
      0.8254571428571428,
      0.8254571428571428,
      0.8254571428571428,
      0.8254571428571428,
      0.8254571428571428,
      0.8254571428571428,
      0.843857142857143,
      0.843857142857143,
      0.843857142857143,
      0.843857142857143,
      0.843857142857143,
      0.843857142857143,
      0.843857142857143,
      0.8540857142857143,
      0.8540857142857143,
      0.8540857142857143,
      0.8540857142857143,
      0.8540857142857143,
      0.8540857142857143,
      0.8540857142857143,
      0.8684571428571428,
      0.8684571428571428,
      0.8684571428571428,
      0.8684571428571428,
      0.8684571428571428,
      0.8684571428571428,
      0.8684571428571428,
      0.8795142857142857,
      0.8795142857142857,
      0.8795142857142857,
      0.8795142857142857,
      0.8795142857142857,
      0.8795142857142857,
      0.8795142857142857,
      0.8906857142857142,
      0.8906857142857142,
      0.8906857142857142,
      0.8906857142857142,
      0.8906857142857142,
      0.8906857142857142,
      0.8906857142857142,
      0.8929,
      0.8929,
      0.8929,
      0.8929,
      0.8929,
      0.8929,
      0.8929,
      0.9027857142857143,
      0.9027857142857143,
      0.9027857142857143,
      0.9027857142857143,
      0.9027857142857143,
      0.9027857142857143,
      0.9027857142857143,
      0.9058142857142857,
      0.9058142857142857,
      0.9058142857142857,
      0.9058142857142857,
      0.9058142857142857,
      0.9058142857142857,
      0.9058142857142857,
      0.9147000000000001,
      0.9147000000000001,
      0.9147000000000001,
      0.9147000000000001,
      0.9147000000000001,
      0.9147000000000001,
      0.9147000000000001,
      0.9172428571428571,
      0.9172428571428571,
      0.9172428571428571,
      0.9172428571428571,
      0.9172428571428571,
      0.9172428571428571,
      0.9172428571428571,
      0.9201142857142857,
      0.9201142857142857,
      0.9201142857142857,
      0.9201142857142857,
      0.9201142857142857,
      0.9201142857142857,
      0.9201142857142857,
      0.9219428571428572,
      0.9219428571428572,
      0.9219428571428572,
      0.9219428571428572,
      0.9219428571428572,
      0.9219428571428572,
      0.9219428571428572,
      0.9297857142857143,
      0.9297857142857143,
      0.9297857142857143,
      0.9297857142857143,
      0.9297857142857143,
      0.9297857142857143,
      0.9297857142857143,
      0.9287428571428571,
      0.9287428571428571,
      0.9287428571428571,
      0.9287428571428571,
      0.9287428571428571,
      0.9287428571428571,
      0.9287428571428571,
      0.9323999999999999,
      0.9323999999999999,
      0.9323999999999999,
      0.9323999999999999,
      0.9323999999999999,
      0.9323999999999999,
      0.9323999999999999,
      0.9371714285714284,
      0.9371714285714284,
      0.9371714285714284,
      0.9371714285714284,
      0.9371714285714284,
      0.9371714285714284,
      0.9371714285714284,
      0.9391857142857143,
      0.9391857142857143,
      0.9391857142857143,
      0.9391857142857143,
      0.9391857142857143,
      0.9391857142857143,
      0.9391857142857143,
      0.9411714285714285,
      0.9411714285714285,
      0.9411714285714285,
      0.9411714285714285,
      0.9411714285714285,
      0.9411714285714285,
      0.9411714285714285,
      0.9420857142857142,
      0.9420857142857142,
      0.9420857142857142,
      0.9420857142857142,
      0.9420857142857142,
      0.9420857142857142,
      0.9420857142857142,
      0.9463714285714284,
      0.9463714285714284,
      0.9463714285714284,
      0.9463714285714284,
      0.9463714285714284,
      0.9463714285714284,
      0.9463714285714284,
      0.9472428571428573,
      0.9472428571428573,
      0.9472428571428573,
      0.9472428571428573,
      0.9472428571428573,
      0.9472428571428573,
      0.9472428571428573,
      0.9486857142857142,
      0.9486857142857142,
      0.9486857142857142,
      0.9486857142857142,
      0.9486857142857142,
      0.9486857142857142,
      0.9486857142857142,
      0.9510571428571426,
      0.9510571428571426,
      0.9510571428571426,
      0.9510571428571426,
      0.9510571428571426,
      0.9510571428571426,
      0.9510571428571426,
      0.9524857142857142,
      0.9524857142857142,
      0.9524857142857142,
      0.9524857142857142,
      0.9524857142857142,
      0.9524857142857142,
      0.9524857142857142,
      0.9526857142857142,
      0.9526857142857142,
      0.9526857142857142,
      0.9526857142857142,
      0.9526857142857142,
      0.9526857142857142,
      0.9526857142857142,
      0.9538857142857142,
      0.9538857142857142,
      0.9538857142857142,
      0.9538857142857142,
      0.9538857142857142,
      0.9538857142857142,
      0.9538857142857142,
      0.955157142857143,
      0.955157142857143,
      0.955157142857143,
      0.955157142857143,
      0.955157142857143,
      0.955157142857143,
      0.955157142857143,
      0.9560142857142856,
      0.9560142857142856,
      0.9560142857142856,
      0.9560142857142856,
      0.9560142857142856,
      0.9560142857142856
    ],
    "latency": [
      5.876712693321027,
      16.185686813412723,
      20.32422580793229,
      17.08830112543855,
      14.252707219258118,
      14.925697333213416,
      14.970779314877934,
      6.530266467335933,
      13.455992588585913,
      7.956175803189079,
      13.614755566381874,
      20.030513281417065,
      15.377427705384225,
      9.713032534525198,
      63.404336411003015,
      40.957753963181624,
      44.68628024176756,
      17.310108848109582,
      59.60987793710217,
      9.401874665669371,
      25.877280326119863,
      25.723173948068176,
      7.446741343914924,
      13.161897192055147,
      6.573207855614517,
      11.651442898787705,
      33.43233318073572,
      14.277853618911635,
      6.619472692378791,
      20.011643895466214,
      12.228374441103988,
      10.034761379810787,
      12.182781959499524,
      7.605098791267884,
      29.833086368907324,
      8.189830593088294,
      19.694455327265747,
      16.828709927567523,
      45.24630893671342,
      29.401290971677454,
      67.5043383484762,
      36.95302717741633,
      8.005812135853638,
      6.5820566007472445,
      102.76922181078706,
      11.823505493593473,
      17.502014254748687,
      23.59950702626257,
      21.236128035228578,
      9.767269530310738,
      13.765307399678798,
      9.556929129317034,
      22.241450434768662,
      22.709397146429563,
      19.711875529847553,
      7.44028314657572,
      28.90618625574156,
      15.320763845723489,
      16.50500072248852,
      10.652815679806974,
      17.990771714348323,
      14.6860536416956,
      6.683073404108639,
      7.903966253786391,
      10.044498433073999,
      12.837259117170296,
      31.171817817473233,
      5.641968209914122,
      57.821724627024075,
      7.062374991938714,
      11.553746482719374,
      22.81399316877558,
      13.581377651370724,
      17.86482533599134,
      9.412695421564578,
      12.206043823388134,
      78.21903733220593,
      50.042824029225336,
      13.428925114361816,
      11.464727926679851,
      1050.1964446219324,
      25.531423042520082,
      122.29831377425513,
      6.878465096763082,
      26.214415873072205,
      5.935910532998615,
      24.62892723546786,
      55.516178715465486,
      16.288707877564953,
      115.29757693258777,
      18.826200668362056,
      12.234397537403693,
      29.71980697223515,
      107.72095959126872,
      10.280944250772224,
      14.47061775729985,
      21.77414263466849,
      4.7179612984995005,
      25.393703269484934,
      17.905576528123238,
      14.496244420954543,
      7.754197282952106,
      13.182579962463056,
      6.0386969353338795,
      12.982658849771155,
      6.545174940747339,
      65.99760879672101,
      15.019054897054287,
      20.468925397219078,
      106.87881184229222,
      9.047324727198598,
      29.941153849921637,
      27.930446097316178,
      11.679654634353145,
      37.57230170009389,
      6.781475265936145,
      103.24297307547717,
      41.64813497778617,
      8.851399593969784,
      19.51286258859348,
      16.60840415138486,
      24.305661814771028,
      10.0013109012756,
      22.049086831317496,
      6.956449872118522,
      10.890824043791316,
      21.12632339667952,
      6.867024094922676,
      27.22942485797486,
      67.30412591975384,
      14.529491564585665,
      30.53018542479024,
      21.115160351963286,
      12.013523846038357,
      7.94600613842795,
      58.85821869397017,
      47.75624030219701,
      83.71208234589658,
      39.086735923664286,
      39.88758333225352,
      50.99961874847348,
      16.503681849720735,
      38.266975790268084,
      7.615940597414085,
      13.166472256411549,
      13.957378251761952,
      55.908814433874745,
      13.139299136878765,
      56.31415156384367,
      9.011192813750744,
      12.187805471480193,
      8.220518656027695,
      103.0998437418401,
      5.6138820171726165,
      7.437833516867492,
      10.424413841146322,
      11.353375583129893,
      8.134804505132163,
      13.427110340030776,
      9.503817077583607,
      16.08393064032396,
      12.298514129590462,
      28.631828476574658,
      21.34540345438035,
      30.672831650927108,
      8.527452369880638,
      19.456096220929677,
      8.240645773386664,
      7.869511727135946,
      19.244447420899075,
      34.80188775100955,
      9.421204349373209,
      596.2296218102522,
      8.497983710333296,
      17.54729248310073,
      14.934678882226292,
      17.948014471422187,
      9.136408671524665,
      21.492134980646778,
      139.80771891697083,
      10.974591890714919,
      14.839380086170971,
      59.74345755396657,
      9.76276196009192,
      7.9480869887849535,
      13.672705207668,
      5.99611960573165,
      32.96116329353505,
      33.602690756324805,
      31.38885059527216,
      8.279345145586891,
      14.197449365769538,
      46.75019902690273,
      19.126144630392194,
      15.167126665009397,
      24.688829781007467,
      13.127789711395543,
      50.638487300830235,
      43.48173888381613,
      14.22644302948543,
      48.14519064270533,
      23.632497105998,
      8.602560709313444,
      19.27402337528333,
      11.67698214566965,
      17.03018129153198,
      14.311672443875075,
      7.213494048522523,
      15.467790822984,
      589.4475849148566,
      12.969035733093557,
      24.97395531185775,
      14.959841890623627,
      11.032287285729929,
      13.439035776735043,
      17.3164849622071,
      17.235625157604115,
      21.413616986871315,
      8.324773194373702,
      23.89391221697007,
      43.33375674285335,
      131.37546015686664,
      15.13417503333831,
      7.492703390906236,
      23.479936310034283,
      26.672286465573166,
      47.77433736459757,
      114.1302958853356,
      8.509431083064964,
      9.042561057572684,
      15.983779073786046,
      11.689543458516294,
      51.55771323324191,
      63.144960385073844,
      15.08480400799539,
      10.89571604308307,
      8.031311470175675,
      6.900098923535908,
      17.738523169321272,
      16.554412149435464,
      36.21873428128556,
      21.321705204723678,
      12.767291333030482,
      60.62188668889706,
      54.26538827333357,
      29.478755155481565,
      9.84192375207086,
      12.659154105856686,
      68.74855327392449,
      8.29607829974227
    ],
    "latency_median": 7.850436149419762,
    "weight_divergence": [
      0.0,
      0.0,
      0.0,
      0.0,
      0.0,
      0.0,
      4.800692626408168,
      4.800692626408168,
      4.800692626408168,
      4.800692626408168,
      4.800692626408168,
      4.800692626408168,
      4.800692626408168,
      3.815946613039289,
      3.815946613039289,
      3.815946613039289,
      3.815946613039289,
      3.815946613039289,
      3.815946613039289,
      3.815946613039289,
      3.2326856000082835,
      3.2326856000082835,
      3.2326856000082835,
      3.2326856000082835,
      3.2326856000082835,
      3.2326856000082835,
      3.2326856000082835,
      2.810054438454764,
      2.810054438454764,
      2.810054438454764,
      2.810054438454764,
      2.810054438454764,
      2.810054438454764,
      2.810054438454764,
      3.2236144542694087,
      3.2236144542694087,
      3.2236144542694087,
      3.2236144542694087,
      3.2236144542694087,
      3.2236144542694087,
      3.2236144542694087,
      3.7381367002214705,
      3.7381367002214705,
      3.7381367002214705,
      3.7381367002214705,
      3.7381367002214705,
      3.7381367002214705,
      3.7381367002214705,
      3.4868840490068704,
      3.4868840490068704,
      3.4868840490068704,
      3.4868840490068704,
      3.4868840490068704,
      3.4868840490068704,
      3.4868840490068704,
      3.3214756420680454,
      3.3214756420680454,
      3.3214756420680454,
      3.3214756420680454,
      3.3214756420680454,
      3.3214756420680454,
      3.3214756420680454,
      3.3210431167057584,
      3.3210431167057584,
      3.3210431167057584,
      3.3210431167057584,
      3.3210431167057584,
      3.3210431167057584,
      3.3210431167057584,
      3.2033563341413225,
      3.2033563341413225,
      3.2033563341413225,
      3.2033563341413225,
      3.2033563341413225,
      3.2033563341413225,
      3.2033563341413225,
      3.1114508083888466,
      3.1114508083888466,
      3.1114508083888466,
      3.1114508083888466,
      3.1114508083888466,
      3.1114508083888466,
      3.1114508083888466,
      4.666393688746862,
      4.666393688746862,
      4.666393688746862,
      4.666393688746862,
      4.666393688746862,
      4.666393688746862,
      4.666393688746862,
      3.0114236559186667,
      3.0114236559186667,
      3.0114236559186667,
      3.0114236559186667,
      3.0114236559186667,
      3.0114236559186667,
      3.0114236559186667,
      3.0553343636648997,
      3.0553343636648997,
      3.0553343636648997,
      3.0553343636648997,
      3.0553343636648997,
      3.0553343636648997,
      3.0553343636648997,
      2.910582848957607,
      2.910582848957607,
      2.910582848957607,
      2.910582848957607,
      2.910582848957607,
      2.910582848957607,
      2.910582848957607,
      2.924434082848685,
      2.924434082848685,
      2.924434082848685,
      2.924434082848685,
      2.924434082848685,
      2.924434082848685,
      2.924434082848685,
      4.295819520950317,
      4.295819520950317,
      4.295819520950317,
      4.295819520950317,
      4.295819520950317,
      4.295819520950317,
      4.295819520950317,
      2.8332624094826833,
      2.8332624094826833,
      2.8332624094826833,
      2.8332624094826833,
      2.8332624094826833,
      2.8332624094826833,
      2.8332624094826833,
      2.793557712009975,
      2.793557712009975,
      2.793557712009975,
      2.793557712009975,
      2.793557712009975,
      2.793557712009975,
      2.793557712009975,
      2.717477934701102,
      2.717477934701102,
      2.717477934701102,
      2.717477934701102,
      2.717477934701102,
      2.717477934701102,
      2.717477934701102,
      2.705552577972412,
      2.705552577972412,
      2.705552577972412,
      2.705552577972412,
      2.705552577972412,
      2.705552577972412,
      2.705552577972412,
      2.6533498764038086,
      2.6533498764038086,
      2.6533498764038086,
      2.6533498764038086,
      2.6533498764038086,
      2.6533498764038086,
      2.6533498764038086,
      2.6191851070949013,
      2.6191851070949013,
      2.6191851070949013,
      2.6191851070949013,
      2.6191851070949013,
      2.6191851070949013,
      2.6191851070949013,
      2.6161148548126216,
      2.6161148548126216,
      2.6161148548126216,
      2.6161148548126216,
      2.6161148548126216,
      2.6161148548126216,
      2.6161148548126216,
      2.5876004355294366,
      2.5876004355294366,
      2.5876004355294366,
      2.5876004355294366,
      2.5876004355294366,
      2.5876004355294366,
      2.5876004355294366,
      2.5980285235813687,
      2.5980285235813687,
      2.5980285235813687,
      2.5980285235813687,
      2.5980285235813687,
      2.5980285235813687,
      2.5980285235813687,
      2.4745097160339355,
      2.4745097160339355,
      2.4745097160339355,
      2.4745097160339355,
      2.4745097160339355,
      2.4745097160339355,
      2.4745097160339355,
      2.4490147999354774,
      2.4490147999354774,
      2.4490147999354774,
      2.4490147999354774,
      2.4490147999354774,
      2.4490147999354774,
      2.4490147999354774,
      2.479454551424299,
      2.479454551424299,
      2.479454551424299,
      2.479454551424299,
      2.479454551424299,
      2.479454551424299,
      2.479454551424299,
      2.3614722660609657,
      2.3614722660609657,
      2.3614722660609657,
      2.3614722660609657,
      2.3614722660609657,
      2.3614722660609657,
      2.3614722660609657,
      2.3734354291643416,
      2.3734354291643416,
      2.3734354291643416,
      2.3734354291643416,
      2.3734354291643416,
      2.3734354291643416,
      2.3734354291643416,
      2.464565072740827,
      2.464565072740827,
      2.464565072740827,
      2.464565072740827,
      2.464565072740827,
      2.464565072740827,
      2.464565072740827,
      2.4074525492531915,
      2.4074525492531915,
      2.4074525492531915,
      2.4074525492531915,
      2.4074525492531915,
      2.4074525492531915,
      2.4074525492531915,
      2.291762488228934,
      2.291762488228934,
      2.291762488228934,
      2.291762488228934,
      2.291762488228934,
      2.291762488228934,
      2.291762488228934,
      3.816532509667533,
      3.816532509667533,
      3.816532509667533,
      3.816532509667533,
      3.816532509667533,
      3.816532509667533
    ]
  }
}