{
  "config": {
    "client_algorithm": "sgd",
    "client_batch_size": 64,
    "client_lr": 0.01,
    "client_n_epochs": 4,
    "client_selection_fraction": 0.3,
    "clients_distribution": "balanced",
    "clients_mobility": true,
    "dataset_distribution": "non_iid",
    "dataset_name": "mnist",
    "debug": false,
    "log_frequency": 1,
    "log_verbosity": 2,
    "lr_warmup": true,
    "mobility_rate": 0.5,
    "model_init": "random",
    "model_type": "mnist",
    "n_clients": 250,
    "n_clusters": 25,
    "server_global_rate": 5,
    "stdout_frequency": 1,
    "stdout_verbosity": 2,
    "stop_condition": "rounds",
    "stop_value": 250,
    "log_file": "log_files/mnist_sgd_lr-warmup-190"
  },
  "results": {
    "rounds": [
      1,
      2,
      3,
      4,
      5,
      6,
      7,
      8,
      9,
      10,
      11,
      12,
      13,
      14,
      15,
      16,
      17,
      18,
      19,
      20,
      21,
      22,
      23,
      24,
      25,
      26,
      27,
      28,
      29,
      30,
      31,
      32,
      33,
      34,
      35,
      36,
      37,
      38,
      39,
      40,
      41,
      42,
      43,
      44,
      45,
      46,
      47,
      48,
      49,
      50,
      51,
      52,
      53,
      54,
      55,
      56,
      57,
      58,
      59,
      60,
      61,
      62,
      63,
      64,
      65,
      66,
      67,
      68,
      69,
      70,
      71,
      72,
      73,
      74,
      75,
      76,
      77,
      78,
      79,
      80,
      81,
      82,
      83,
      84,
      85,
      86,
      87,
      88,
      89,
      90,
      91,
      92,
      93,
      94,
      95,
      96,
      97,
      98,
      99,
      100,
      101,
      102,
      103,
      104,
      105,
      106,
      107,
      108,
      109,
      110,
      111,
      112,
      113,
      114,
      115,
      116,
      117,
      118,
      119,
      120,
      121,
      122,
      123,
      124,
      125,
      126,
      127,
      128,
      129,
      130,
      131,
      132,
      133,
      134,
      135,
      136,
      137,
      138,
      139,
      140,
      141,
      142,
      143,
      144,
      145,
      146,
      147,
      148,
      149,
      150,
      151,
      152,
      153,
      154,
      155,
      156,
      157,
      158,
      159,
      160,
      161,
      162,
      163,
      164,
      165,
      166,
      167,
      168,
      169,
      170,
      171,
      172,
      173,
      174,
      175,
      176,
      177,
      178,
      179,
      180,
      181,
      182,
      183,
      184,
      185,
      186,
      187,
      188,
      189,
      190,
      191,
      192,
      193,
      194,
      195,
      196,
      197,
      198,
      199,
      200,
      201,
      202,
      203,
      204,
      205,
      206,
      207,
      208,
      209,
      210,
      211,
      212,
      213,
      214,
      215,
      216,
      217,
      218,
      219,
      220,
      221,
      222,
      223,
      224,
      225,
      226,
      227,
      228,
      229,
      230,
      231,
      232,
      233,
      234,
      235,
      236,
      237,
      238,
      239,
      240,
      241,
      242,
      243,
      244,
      245,
      246,
      247,
      248,
      249,
      250
    ],
    "train_accuracy": [
      0.0,
      0.0,
      0.0,
      0.0,
      0.0,
      0.0,
      0.0,
      0.0,
      0.0,
      0.0,
      0.0,
      0.0,
      0.0,
      0.0,
      0.0,
      0.0,
      0.0,
      0.0,
      0.0,
      0.0,
      0.0,
      0.0,
      0.0,
      0.0,
      0.0,
      0.0,
      0.0,
      0.0,
      0.0,
      0.0,
      0.0,
      0.0,
      0.0,
      0.0,
      0.0,
      0.0,
      0.0,
      0.0,
      0.0,
      0.0,
      0.0,
      0.0,
      0.0,
      0.0,
      0.0,
      0.0,
      0.0,
      0.0,
      0.0,
      0.0,
      0.0,
      0.0,
      0.0,
      0.0,
      0.0,
      0.0,
      0.0,
      0.0,
      0.0,
      0.0,
      0.0,
      0.0,
      0.0,
      0.0,
      0.0,
      0.0,
      0.0,
      0.0,
      0.0,
      0.0,
      0.0,
      0.0,
      0.0,
      0.0,
      0.0,
      0.0,
      0.0,
      0.0,
      0.0,
      0.0,
      0.0,
      0.0,
      0.0,
      0.0,
      0.0,
      0.0,
      0.0,
      0.0,
      0.0,
      0.0,
      0.0,
      0.0,
      0.0,
      0.0,
      0.0,
      0.0,
      0.0,
      0.0,
      0.0,
      0.0,
      0.0,
      0.0,
      0.0,
      0.0,
      0.0,
      0.0,
      0.0,
      0.0,
      0.0,
      0.0,
      0.0,
      0.0,
      0.0,
      0.0,
      0.0,
      0.0,
      0.0,
      0.0,
      0.0,
      0.0,
      0.0,
      0.0,
      0.0,
      0.0,
      0.0,
      0.0,
      0.0,
      0.0,
      0.0,
      0.0,
      0.0,
      0.0,
      0.0,
      0.0,
      0.0,
      0.0,
      0.0,
      0.0,
      0.0,
      0.0,
      0.0,
      0.0,
      0.0,
      0.0,
      0.0,
      0.0,
      0.0,
      0.0,
      0.0,
      0.0,
      0.0,
      0.0,
      0.0,
      0.0,
      0.0,
      0.0,
      0.0,
      0.0,
      0.0,
      0.0,
      0.0,
      0.0,
      0.0,
      0.0,
      0.0,
      0.0,
      0.0,
      0.0,
      0.0,
      0.0,
      0.0,
      0.0,
      0.0,
      0.0,
      0.0,
      0.0,
      0.0,
      0.0,
      0.0,
      0.0,
      0.0,
      0.0,
      0.0,
      0.0,
      0.0,
      0.0,
      0.0,
      0.0,
      0.0,
      0.0,
      0.0,
      0.0,
      0.0,
      0.0,
      0.0,
      0.0,
      0.0,
      0.0,
      0.0,
      0.0,
      0.0,
      0.0,
      0.0,
      0.0,
      0.0,
      0.0,
      0.0,
      0.0,
      0.0,
      0.0,
      0.0,
      0.0,
      0.0,
      0.0,
      0.0,
      0.0,
      0.0,
      0.0,
      0.0,
      0.0,
      0.0,
      0.0,
      0.0,
      0.0,
      0.0,
      0.0,
      0.0,
      0.0,
      0.0,
      0.0,
      0.0,
      0.0,
      0.0,
      0.0,
      0.0,
      0.0,
      0.0,
      0.0,
      0.0,
      0.0,
      0.0,
      0.0,
      0.0,
      0.0,
      0.0,
      0.0,
      0.0,
      0.0,
      0.0,
      0.0
    ],
    "test_accuracy": [
      0.0,
      0.0,
      0.0,
      0.0,
      0.2864,
      0.2864,
      0.2864,
      0.2864,
      0.2864,
      0.4413555555555555,
      0.4413555555555555,
      0.4413555555555555,
      0.4413555555555555,
      0.4413555555555555,
      0.4734777777777777,
      0.4734777777777777,
      0.4734777777777777,
      0.4734777777777777,
      0.4734777777777777,
      0.4785444444444445,
      0.4785444444444445,
      0.4785444444444445,
      0.4785444444444445,
      0.4785444444444445,
      0.6926111111111111,
      0.6926111111111111,
      0.6926111111111111,
      0.6926111111111111,
      0.6926111111111111,
      0.7961333333333334,
      0.7961333333333334,
      0.7961333333333334,
      0.7961333333333334,
      0.7961333333333334,
      0.8812333333333333,
      0.8812333333333333,
      0.8812333333333333,
      0.8812333333333333,
      0.8812333333333333,
      0.9153555555555556,
      0.9153555555555556,
      0.9153555555555556,
      0.9153555555555556,
      0.9153555555555556,
      0.9405333333333334,
      0.9405333333333334,
      0.9405333333333334,
      0.9405333333333334,
      0.9405333333333334,
      0.9513666666666667,
      0.9513666666666667,
      0.9513666666666667,
      0.9513666666666667,
      0.9513666666666667,
      0.9559777777777778,
      0.9559777777777778,
      0.9559777777777778,
      0.9559777777777778,
      0.9559777777777778,
      0.9616666666666666,
      0.9616666666666666,
      0.9616666666666666,
      0.9616666666666666,
      0.9616666666666666,
      0.9644222222222222,
      0.9644222222222222,
      0.9644222222222222,
      0.9644222222222222,
      0.9644222222222222,
      0.9683444444444445,
      0.9683444444444445,
      0.9683444444444445,
      0.9683444444444445,
      0.9683444444444445,
      0.9698555555555555,
      0.9698555555555555,
      0.9698555555555555,
      0.9698555555555555,
      0.9698555555555555,
      0.9722555555555555,
      0.9722555555555555,
      0.9722555555555555,
      0.9722555555555555,
      0.9722555555555555,
      0.9736888888888888,
      0.9736888888888888,
      0.9736888888888888,
      0.9736888888888888,
      0.9736888888888888,
      0.9750888888888889,
      0.9750888888888889,
      0.9750888888888889,
      0.9750888888888889,
      0.9750888888888889,
      0.9762666666666666,
      0.9762666666666666,
      0.9762666666666666,
      0.9762666666666666,
      0.9762666666666666,
      0.977488888888889,
      0.977488888888889,
      0.977488888888889,
      0.977488888888889,
      0.977488888888889,
      0.9786333333333334,
      0.9786333333333334,
      0.9786333333333334,
      0.9786333333333334,
      0.9786333333333334,
      0.9796666666666666,
      0.9796666666666666,
      0.9796666666666666,
      0.9796666666666666,
      0.9796666666666666,
      0.9795111111111112,
      0.9795111111111112,
      0.9795111111111112,
      0.9795111111111112,
      0.9795111111111112,
      0.9810000000000001,
      0.9810000000000001,
      0.9810000000000001,
      0.9810000000000001,
      0.9810000000000001,
      0.9815444444444446,
      0.9815444444444446,
      0.9815444444444446,
      0.9815444444444446,
      0.9815444444444446,
      0.9823111111111111,
      0.9823111111111111,
      0.9823111111111111,
      0.9823111111111111,
      0.9823111111111111,
      0.9824111111111111,
      0.9824111111111111,
      0.9824111111111111,
      0.9824111111111111,
      0.9824111111111111,
      0.9832333333333334,
      0.9832333333333334,
      0.9832333333333334,
      0.9832333333333334,
      0.9832333333333334,
      0.9835222222222221,
      0.9835222222222221,
      0.9835222222222221,
      0.9835222222222221,
      0.9835222222222221,
      0.9841222222222221,
      0.9841222222222221,
      0.9841222222222221,
      0.9841222222222221,
      0.9841222222222221,
      0.9842444444444444,
      0.9842444444444444,
      0.9842444444444444,
      0.9842444444444444,
      0.9842444444444444,
      0.9847000000000001,
      0.9847000000000001,
      0.9847000000000001,
      0.9847000000000001,
      0.9847000000000001,
      0.9851333333333334,
      0.9851333333333334,
      0.9851333333333334,
      0.9851333333333334,
      0.9851333333333334,
      0.9852333333333334,
      0.9852333333333334,
      0.9852333333333334,
      0.9852333333333334,
      0.9852333333333334,
      0.9852666666666667,
      0.9852666666666667,
      0.9852666666666667,
      0.9852666666666667,
      0.9852666666666667,
      0.9857666666666667,
      0.9857666666666667,
      0.9857666666666667,
      0.9857666666666667,
      0.9857666666666667,
      0.986188888888889,
      0.986188888888889,
      0.986188888888889,
      0.986188888888889,
      0.986188888888889,
      0.9859111111111111,
      0.9859111111111111,
      0.9859111111111111,
      0.9859111111111111,
      0.9859111111111111,
      0.9861000000000002,
      0.9861000000000002,
      0.9861000000000002,
      0.9861000000000002,
      0.9861000000000002,
      0.9868777777777777,
      0.9868777777777777,
      0.9868777777777777,
      0.9868777777777777,
      0.9868777777777777,
      0.9869000000000001,
      0.9869000000000001,
      0.9869000000000001,
      0.9869000000000001,
      0.9869000000000001,
      0.9871444444444445,
      0.9871444444444445,
      0.9871444444444445,
      0.9871444444444445,
      0.9871444444444445,
      0.9871666666666666,
      0.9871666666666666,
      0.9871666666666666,
      0.9871666666666666,
      0.9871666666666666,
      0.9870777777777778,
      0.9870777777777778,
      0.9870777777777778,
      0.9870777777777778,
      0.9870777777777778,
      0.9873888888888889,
      0.9873888888888889,
      0.9873888888888889,
      0.9873888888888889,
      0.9873888888888889,
      0.9875333333333334,
      0.9875333333333334,
      0.9875333333333334,
      0.9875333333333334,
      0.9875333333333334,
      0.9874666666666666,
      0.9874666666666666,
      0.9874666666666666,
      0.9874666666666666,
      0.9874666666666666,
      0.9876222222222222,
      0.9876222222222222,
      0.9876222222222222,
      0.9876222222222222,
      0.9876222222222222,
      0.9877,
      0.9877,
      0.9877,
      0.9877,
      0.9877,
      0.9878444444444444
    ],
    "latency": [
      78.40881964174194,
      7.927367058836246,
      20.870368150851757,
      20.750885314479614,
      17.59088748734908,
      42.33787156140902,
      14.637792295699015,
      51.97407591512326,
      19.92315700201997,
      19.188535847467254,
      24.090113559310236,
      77.5592447784458,
      16.811460176432185,
      9.635983112011271,
      32.9915658267626,
      37.69879171191518,
      8.749115628933115,
      25.09398691691422,
      39.888266144907014,
      10.499442143704247,
      31.054640862412477,
      13.132121813371985,
      22.354936710979707,
      15.531021391705227,
      15.090380662375594,
      5.219492946186607,
      29.908166584249837,
      10.544844219657632,
      24.857551741267798,
      10.19875181645374,
      351.7993222429518,
      19.560614107543078,
      14.115879838827096,
      10.725071026913536,
      11.77778010983658,
      15.258310775895067,
      16.60260648391492,
      13.716326727344857,
      31.23473058260079,
      33.56051796035987,
      5.0919219492399375,
      12.708307466440882,
      12.573247480514675,
      17.71638088136185,
      13.178939391826981,
      12.016701798007006,
      7.636774242997774,
      36.622133393460565,
      24.56650617591247,
      36.03058023675812,
      31.683660867901917,
      34.9505978093872,
      18.215268023569973,
      13.691846718570092,
      21.54735145481248,
      46.72847315948233,
      12.118124021358193,
      8.873706629342873,
      140.26629822803721,
      25.06189208642332,
      15.477524094245878,
      15.71877215885426,
      32.77499791311014,
      25.324240537260017,
      11.951643348008023,
      4.430003216079357,
      110.19909552128404,
      11.272234500676387,
      15.27452258039422,
      24.005948753310292,
      20.485680901726113,
      18.305878644076177,
      431.02542989984516,
      10.923904359641464,
      10.092200284638396,
      220.5453262343976,
      13.02840687936897,
      14.504482486446678,
      81.28534649776827,
      47.66334533109083,
      24.129799758466117,
      27.955890169999396,
      14.633851044467903,
      26.021985280604266,
      75.86394894308776,
      18.121780004067414,
      25.2249056275147,
      31.187437365256393,
      15.245828429392803,
      26.503031993623633,
      12.120303269682026,
      42.242965467859264,
      10.895772558045037,
      7.504775191434797,
      7.803247777362343,
      9.584321546663675,
      192.62279138203274,
      19.51105717836782,
      5.877015581018995,
      11.607278425242713,
      14.450670915239701,
      27.625308805504847,
      9.383184089560427,
      8.956034397495042,
      35.72114464043987,
      49.66247298854172,
      14.508676911341713,
      16.174826457169633,
      13.545456395953467,
      15.978015530319741,
      22.58994712675696,
      12.446184825479682,
      10.630986881906482,
      11.978322568708208,
      62.43065769687678,
      37.942873888400214,
      5.623419798214851,
      12.662227914215416,
      28.13839972843114,
      23.39161783299843,
      14.470532725217007,
      8.985707810835226,
      8.35448535015085,
      35.13241953706427,
      13.041917628309216,
      18.441445337919763,
      25.1350394511662,
      21.76757041463411,
      24.05793700586713,
      136.02210250195708,
      14.084505215002958,
      30.653280853318115,
      9.044464840585865,
      26.923659676438973,
      15.086979336592242,
      8.923082694360033,
      11.955824349689138,
      6.862432150904987,
      8.920071538415764,
      58.97697884737102,
      16.327377160096713,
      30.099917867452852,
      13.76317654564413,
      38.4330296431638,
      23.810526692236643,
      36.814120763987475,
      17.075223700353078,
      8.919232699503553,
      9.898791015840512,
      13.32463025189465,
      7.356838780563085,
      13.658896036759325,
      33.244204201146104,
      11.799051578748665,
      6.896311605105847,
      6.415324845546947,
      12.22636193659045,
      26.09562891427394,
      21.79683616115517,
      18.907018431992487,
      11.304486024724602,
      13.273183748950053,
      11.463546168345752,
      26.27601845596614,
      4.885453650340286,
      13.334280756902832,
      20.208157431519133,
      20.228482463602955,
      9.48332282816037,
      8.173603987448972,
      10.435351101567397,
      23.509963970385517,
      10.726513644545063,
      43.479911307568635,
      11.29031238902753,
      11.536608814832254,
      15.809461820531073,
      15.49280201160563,
      63.96216902410036,
      51.354540551415184,
      7.579172005326205,
      9.38787815167998,
      11.82564105311611,
      8.993556638357534,
      17.57649710110199,
      12.319424630201832,
      6.76960791915069,
      123.44440460322691,
      11.058060482503546,
      10.255032482942516,
      60.47870188489363,
      11.154127362887216,
      90.9074873222882,
      158.17668523925792,
      20.252226992353894,
      11.721999839485461,
      44.65767394977774,
      6794.684721164297,
      10.776304371359924,
      35.2910243714409,
      19.080391924988742,
      7.767433588370298,
      8.633917268635399,
      10.925888754778907,
      11.487904793539228,
      351.00945111822216,
      16.55952722625103,
      39.54421889381525,
      22.528579569460106,
      12.13090738039411,
      6.0958321410497955,
      11.573561956648376,
      17.865322891419638,
      46.94275082541928,
      10.542581499938654,
      22.813147209287845,
      8.292446726969523,
      18.218358736088067,
      15.44128753873859,
      25.067179744976706,
      12.955944790289257,
      9.467440029180155,
      6.5267597507778525,
      10.978039143313755,
      11.336409703571277,
      11.860405741488853,
      34.16622519637378,
      12.580028662692555,
      92.42170111858516,
      15.005898140093219,
      16.23172073684389,
      119.69630818120326,
      43.08065782883835,
      111.87377386803995,
      325.8383312251271,
      9.911336324453035,
      28.02602445660031,
      73.86750125004082,
      14.724451719739807,
      20.78376459750168,
      32.070740780975854,
      9.504989001471941,
      73.02912869746565,
      15.130295156644777,
      9.289458347561983,
      7.7825097556209935,
      9.67495630807949,
      23.26503570503339,
      5.782637980254386,
      18.603517272217342
    ],
    "latency_median": 7.731855663799074,
    "weight_divergence": [
      0.0,
      0.0,
      0.0,
      0.0,
      12.490189552307129,
      12.490189552307129,
      12.490189552307129,
      12.490189552307129,
      12.490189552307129,
      35.465537812974716,
      35.465537812974716,
      35.465537812974716,
      35.465537812974716,
      35.465537812974716,
      44.96942138671875,
      44.96942138671875,
      44.96942138671875,
      44.96942138671875,
      44.96942138671875,
      44.74286778767903,
      44.74286778767903,
      44.74286778767903,
      44.74286778767903,
      44.74286778767903,
      29.736373477511936,
      29.736373477511936,
      29.736373477511936,
      29.736373477511936,
      29.736373477511936,
      22.746003044976128,
      22.746003044976128,
      22.746003044976128,
      22.746003044976128,
      22.746003044976128,
      15.187931696573893,
      15.187931696573893,
      15.187931696573893,
      15.187931696573893,
      15.187931696573893,
      11.945443789164225,
      11.945443789164225,
      11.945443789164225,
      11.945443789164225,
      11.945443789164225,
      9.532228946685791,
      9.532228946685791,
      9.532228946685791,
      9.532228946685791,
      9.532228946685791,
      9.083554585774738,
      9.083554585774738,
      9.083554585774738,
      9.083554585774738,
      9.083554585774738,
      8.214630815717909,
      8.214630815717909,
      8.214630815717909,
      8.214630815717909,
      8.214630815717909,
      8.086499426099989,
      8.086499426099989,
      8.086499426099989,
      8.086499426099989,
      8.086499426099989,
      7.167655415005154,
      7.167655415005154,
      7.167655415005154,
      7.167655415005154,
      7.167655415005154,
      6.6819059054056815,
      6.6819059054056815,
      6.6819059054056815,
      6.6819059054056815,
      6.6819059054056815,
      7.496020052168104,
      7.496020052168104,
      7.496020052168104,
      7.496020052168104,
      7.496020052168104,
      6.3334790865580235,
      6.3334790865580235,
      6.3334790865580235,
      6.3334790865580235,
      6.3334790865580235,
      6.098875098758274,
      6.098875098758274,
      6.098875098758274,
      6.098875098758274,
      6.098875098758274,
      5.665733761257596,
      5.665733761257596,
      5.665733761257596,
      5.665733761257596,
      5.665733761257596,
      5.908694214291042,
      5.908694214291042,
      5.908694214291042,
      5.908694214291042,
      5.908694214291042,
      5.398187398910523,
      5.398187398910523,
      5.398187398910523,
      5.398187398910523,
      5.398187398910523,
      5.189254151450262,
      5.189254151450262,
      5.189254151450262,
      5.189254151450262,
      5.189254151450262,
      4.983306778801812,
      4.983306778801812,
      4.983306778801812,
      4.983306778801812,
      4.983306778801812,
      5.245940287907918,
      5.245940287907918,
      5.245940287907918,
      5.245940287907918,
      5.245940287907918,
      4.804190317789713,
      4.804190317789713,
      4.804190317789713,
      4.804190317789713,
      4.804190317789713,
      4.739754835764567,
      4.739754835764567,
      4.739754835764567,
      4.739754835764567,
      4.739754835764567,
      5.079592810736762,
      5.079592810736762,
      5.079592810736762,
      5.079592810736762,
      5.079592810736762,
      4.6931370629204645,
      4.6931370629204645,
      4.6931370629204645,
      4.6931370629204645,
      4.6931370629204645,
      4.405495431688097,
      4.405495431688097,
      4.405495431688097,
      4.405495431688097,
      4.405495431688097,
      5.6696043544345445,
      5.6696043544345445,
      5.6696043544345445,
      5.6696043544345445,
      5.6696043544345445,
      4.449313931994968,
      4.449313931994968,
      4.449313931994968,
      4.449313931994968,
      4.449313931994968,
      4.435848818884956,
      4.435848818884956,
      4.435848818884956,
      4.435848818884956,
      4.435848818884956,
      4.454116317960951,
      4.454116317960951,
      4.454116317960951,
      4.454116317960951,
      4.454116317960951,
      4.208657052781847,
      4.208657052781847,
      4.208657052781847,
      4.208657052781847,
      4.208657052781847,
      4.071754720475939,
      4.071754720475939,
      4.071754720475939,
      4.071754720475939,
      4.071754720475939,
      4.405231820212471,
      4.405231820212471,
      4.405231820212471,
      4.405231820212471,
      4.405231820212471,
      4.407702234056261,
      4.407702234056261,
      4.407702234056261,
      4.407702234056261,
      4.407702234056261,
      4.090410868326822,
      4.090410868326822,
      4.090410868326822,
      4.090410868326822,
      4.090410868326822,
      4.099923080868191,
      4.099923080868191,
      4.099923080868191,
      4.099923080868191,
      4.099923080868191,
      4.140873750050863,
      4.140873750050863,
      4.140873750050863,
      4.140873750050863,
      4.140873750050863,
      3.9531984329223633,
      3.9531984329223633,
      3.9531984329223633,
      3.9531984329223633,
      3.9531984329223633,
      5.082294384638468,
      5.082294384638468,
      5.082294384638468,
      5.082294384638468,
      5.082294384638468,
      3.7564013534122047,
      3.7564013534122047,
      3.7564013534122047,
      3.7564013534122047,
      3.7564013534122047,
      3.905899365743001,
      3.905899365743001,
      3.905899365743001,
      3.905899365743001,
      3.905899365743001,
      5.079535219404433,
      5.079535219404433,
      5.079535219404433,
      5.079535219404433,
      5.079535219404433,
      3.729905658298069,
      3.729905658298069,
      3.729905658298069,
      3.729905658298069,
      3.729905658298069,
      4.056723091337417,
      4.056723091337417,
      4.056723091337417,
      4.056723091337417,
      4.056723091337417,
      3.804547839694553,
      3.804547839694553,
      3.804547839694553,
      3.804547839694553,
      3.804547839694553,
      3.9950785107082787,
      3.9950785107082787,
      3.9950785107082787,
      3.9950785107082787,
      3.9950785107082787,
      3.9279480510287814,
      3.9279480510287814,
      3.9279480510287814,
      3.9279480510287814,
      3.9279480510287814,
      3.717892090479533
    ]
  }
}